CHANGES.txt
MANIFEST.in
README.md
config.md
setup.py
PGeo.egg-info/PKG-INFO
PGeo.egg-info/SOURCES.txt
PGeo.egg-info/dependency_links.txt
PGeo.egg-info/requires.txt
PGeo.egg-info/top_level.txt
docs/apache_falsk_configuration.md
pgeo/.gitignore
pgeo/__init__.py
pgeo/__init__.pyc
pgeo/config/.gitignore
pgeo/config/__init__.py
pgeo/config/__init__.pyc
pgeo/config/epydoc.config
pgeo/config/settings.py
pgeo/config/settings.pyc
pgeo/config/data_providers/__gaul2modis.json
pgeo/config/data_providers/__trmm1.json
pgeo/config/data_providers/modis.json
pgeo/config/data_providers/trmm2.json
pgeo/config/metadata/metadata.json
pgeo/config/metadata/metadata_example.json
pgeo/config/metadata/raster_example.json
pgeo/config/metadata/templates/core.json
pgeo/config/metadata/templates/modis.json
pgeo/config/metadata/templates/old_core.json
pgeo/config/metadata/templates/raster.json
pgeo/config/stats/__init__.py
pgeo/config/stats/__init__.pyc
pgeo/config/stats/default_statistics.py
pgeo/config/stats/default_statistics.pyc
pgeo/config/stats/gaul0.json
pgeo/config/stats/gaul0.sql
pgeo/config/stats/gaul0_indexes.sql
pgeo/dataproviders/__init__.py
pgeo/dataproviders/__init__.pyc
pgeo/dataproviders/modis.py
pgeo/dataproviders/modis.pyc
pgeo/dataproviders/trmm.pyc
pgeo/dataproviders/trmm1.py
pgeo/dataproviders/trmm1.pyc
pgeo/dataproviders/trmm2.py
pgeo/dataproviders/trmm2.pyc
pgeo/db/.gitignore
pgeo/db/__init__.py
pgeo/db/__init__.pyc
pgeo/db/mongo/__init__.py
pgeo/db/mongo/__init__.pyc
pgeo/db/mongo/common.py
pgeo/db/mongo/common.pyc
pgeo/db/mongo/search.pyc
pgeo/db/mongo/metadata/__init__.pyc
pgeo/db/mongo/metadata/db.pyc
pgeo/db/postgresql/.gitignore
pgeo/db/postgresql/__init__.py
pgeo/db/postgresql/__init__.pyc
pgeo/db/postgresql/common.py
pgeo/db/postgresql/common.pyc
pgeo/db/postgresql/postgis_utils/__init__.py
pgeo/db/postgresql/postgis_utils/__init__.pyc
pgeo/db/postgresql/postgis_utils/shapefile.py
pgeo/db/postgresql/postgis_utils/shapefile.pyc
pgeo/db/postgresql/postgis_utils/util.py
pgeo/db/postgresql/postgis_utils/util.pyc
pgeo/error/.gitignore
pgeo/error/__init__.py
pgeo/error/__init__.pyc
