Metadata-Version: 1.0
Name: PGeo
Version: 0.1.10
Summary: PGeo module.
Home-page: http://pypi.python.org/pypi/PGeo/
Author: Simone Murzilli; Guido Barbaglia
Author-email: geobrickspy@gmail.com
License: LICENSE.txt
Platform: UNKNOWN
